cmaes/__init__.py
cmaes/optim_L2M2019Ctrl_2D.py
cmaes/optim_par_L2M2019Ctrl.py
cmaes/optim_par_L2M2019Ctrl_2D.py
cmaes/plot_cma.py
cmaes/solver.py
cmaes/solver_cma.py
cmaes/test_problems.py
cmaes/utils.py
envs/__init__.py
envs/control/__init__.py
envs/control/loco_reflex_song2019.py
envs/target/__init__.py
envs/target/test_v_tgt.py
envs/target/test_v_tgt_sink.py
envs/target/v_tgt_field.py
osim/__init__.py
osim/control/__init__.py
osim/control/osim_loco_reflex_song2019.py
osim/env/__init__.py
osim/env/arm.py
osim/env/osim.py
osim/env/utils/__init__.py
osim/env/utils/mygym.py
osim/env/utils/rllab.py
osim/http/__init__.py
osim/http/client.py
osim/models/MoBL_ARMS_J.osim
osim/models/MoBL_ARMS_J_Simple_032118.osim
osim/models/arm26.osim
osim/models/arm2dof6musc.osim
osim/models/gait14dof22musc_20170320.osim
osim/models/gait14dof22musc_planar_20170320.osim
osim/models/gait14dof22musc_planar_pros_20180507.osim
osim/models/gait14dof22musc_pros_20180507.osim
osim/models/gait9dof18musc.osim
osim/models/gait9dof18musc_20170320.osim
osim/models/gait9dof18musc_pros_20180507.osim
osim/models/hop8dof9musc.osim
osim/models/ue_RL.osim
osim/models/Geometry/1mc.vtp
osim/models/Geometry/2distph.vtp
osim/models/Geometry/2mc.vtp
osim/models/Geometry/2midph.vtp
osim/models/Geometry/2proxph.vtp
osim/models/Geometry/3distph.vtp
osim/models/Geometry/3mc.vtp
osim/models/Geometry/3midph.vtp
osim/models/Geometry/3proxph.vtp
osim/models/Geometry/4distph.vtp
osim/models/Geometry/4mc.vtp
osim/models/Geometry/4midph.vtp
osim/models/Geometry/4proxph.vtp
osim/models/Geometry/5distph.vtp
osim/models/Geometry/5mc.vtp
osim/models/Geometry/5midph.vtp
osim/models/Geometry/5proxph.vtp
osim/models/Geometry/Cube.vtp
osim/models/Geometry/Grass.vtp
osim/models/Geometry/Sky.vtp
osim/models/Geometry/arm_r_1mc.vtp
osim/models/Geometry/arm_r_2distph.vtp
osim/models/Geometry/arm_r_2mc.vtp
osim/models/Geometry/arm_r_2midph.vtp
osim_rl-3.0.6.dist-info/DESCRIPTION.rst
osim_rl-3.0.6.dist-info/METADATA
osim_rl-3.0.6.dist-info/RECORD
osim_rl-3.0.6.dist-info/WHEEL
osim_rl-3.0.6.dist-info/metadata.json
osim_rl-3.0.6.dist-info/top_level.txt
